UEVaultManager/__init__.py
UEVaultManager/cli.py
UEVaultManager/core.py
UEVaultManager/api/__init__.py
UEVaultManager/api/egs.py
UEVaultManager/api/uevm.py
UEVaultManager/assets/UEVM_200x200.png
UEVaultManager/assets/checked_16.png
UEVaultManager/assets/main.ico
UEVaultManager/assets/unchecked_16.png
UEVaultManager/downloader/__init__.py
UEVaultManager/downloader/mp/DLManagerClass.py
UEVaultManager/downloader/mp/__init__.py
UEVaultManager/downloader/mp/manager.py
UEVaultManager/downloader/mp/workers.py
UEVaultManager/lfs/EPCLFSClass.py
UEVaultManager/lfs/UEVMLFSClass.py
UEVaultManager/lfs/__init__.py
UEVaultManager/lfs/egl.py
UEVaultManager/lfs/uevmlfs.py
UEVaultManager/lfs/utils.py
UEVaultManager/lfs/windows_helpers.py
UEVaultManager/models/AppConfigClass.py
UEVaultManager/models/Asset.py
UEVaultManager/models/ChunkClass.py
UEVaultManager/models/EGLManifestClass.py
UEVaultManager/models/UCRequest.py
UEVaultManager/models/UCResponse.py
UEVaultManager/models/UEAssetClass.py
UEVaultManager/models/UEAssetDbHandlerClass.py
UEVaultManager/models/UEAssetScraperClass.py
UEVaultManager/models/__init__.py
UEVaultManager/models/app.py
UEVaultManager/models/chunk.py
UEVaultManager/models/config.py
UEVaultManager/models/csv_data.py
UEVaultManager/models/csv_sql_fields.py
UEVaultManager/models/downloading.py
UEVaultManager/models/egl.py
UEVaultManager/models/exceptions.py
UEVaultManager/models/json_manifest.py
UEVaultManager/models/manifest.py
UEVaultManager/models/types.py
UEVaultManager/tkgui/__init__.py
UEVaultManager/tkgui/main.py
UEVaultManager/tkgui/modules/DisplayContentWindowClass.py
UEVaultManager/tkgui/modules/EditCellWindowClass.py
UEVaultManager/tkgui/modules/EditRowWindowClass.py
UEVaultManager/tkgui/modules/EditableTableClass.py
UEVaultManager/tkgui/modules/ExtendedWidgetClasses.py
UEVaultManager/tkgui/modules/FakeProgressWindowClass.py
UEVaultManager/tkgui/modules/GUISettingsClass.py
UEVaultManager/tkgui/modules/ProgressWindowClass.py
UEVaultManager-1.12.6.dist-info/LICENSE
UEVaultManager-1.12.6.dist-info/METADATA
UEVaultManager-1.12.6.dist-info/WHEEL
UEVaultManager-1.12.6.dist-info/entry_points.txt
UEVaultManager-1.12.6.dist-info/top_level.txt
UEVaultManager-1.12.6.dist-info/RECORD
