Metadata-Version: 2.1
Name: UEVaultManager
Version: 1.12.6
Summary: Free and open-source replacement for the Epic Games Launcher application, mainly to manage the assets for Unreal Engine
Home-page: https://github.com/LaurentOngaro/UEVaultManager
Author: Laurent Ongaro
Author-email: laurent@gameamea.com
License: GPL-3
Classifier: License :: OSI Approved :: BSD License
Classifier: Programming Language :: Python :: 3.9
Classifier: Programming Language :: Python :: 3.10
Classifier: Programming Language :: Python :: 3.11
Classifier: Programming Language :: Python :: 3.12
Classifier: Operating System :: OS Independent
Classifier: Development Status :: 5 - Production/Stable
Requires-Python: >=3.9
License-File: LICENSE
Requires-Dist: requirements-parser
Requires-Dist: setuptools
Requires-Dist: Pillow >=10.0.2
Requires-Dist: beautifulsoup4 ~=4.11
Requires-Dist: future >=1.0.0
Requires-Dist: pandastable
Requires-Dist: matplotlib ==3.8.4
Requires-Dist: pandas >=2.0
Requires-Dist: pywebview >=5.0.5
Requires-Dist: requests >=2.0
Requires-Dist: screeninfo >=0.8
Requires-Dist: setuptools >=69.2.0
Requires-Dist: termcolor >=2.3
Requires-Dist: ttkbootstrap >=1.10
Requires-Dist: packaging >=24.0
Requires-Dist: Faker >=24.4.0
Requires-Dist: rapidfuzz
Requires-Dist: tkhtmlview >=0.2.0
Requires-Dist: Jinja2
Requires-Dist: selenium
Requires-Dist: nodriver
Requires-Dist: reqdriver
Provides-Extra: webview
Requires-Dist: pywebview >=3.4 ; extra == 'webview'
Provides-Extra: webview_gtk
Requires-Dist: pywebview >=3.4 ; extra == 'webview_gtk'
Requires-Dist: PyGObject ; extra == 'webview_gtk'
